xapian/__init__.py
xapian/_xapian.cpython-311-x86_64-linux-gnu.so
xapian/bindings.py
xapianpy.libs/libxapian-b71f8c65.so.30.12.3
xapianpy-1.4.22.post2406040406.dist-info/WHEEL
xapianpy-1.4.22.post2406040406.dist-info/top_level.txt
xapianpy-1.4.22.post2406040406.dist-info/RECORD
xapianpy-1.4.22.post2406040406.dist-info/METADATA
